unfazed/cli.py
unfazed/const.py
unfazed/app/__init__.py
unfazed/app/base.py
unfazed/app/registry.py
unfazed/cache/__init__.py
unfazed/cache/decorators.py
unfazed/cache/handler.py
unfazed/cache/lifespan.py
unfazed/cache/backends/locmem.py
unfazed/cache/backends/redis/__init__.py
unfazed/cache/backends/redis/defaultclient.py
unfazed/cache/backends/redis/serializedclient.py
unfazed/cache/compressors/zlib.py
unfazed/cache/serializers/pickle.py
unfazed/command/__init__.py
unfazed/command/base.py
unfazed/command/registry.py
unfazed/command/internal/create_superuser.py
unfazed/command/internal/export_openapi.py
unfazed/command/internal/shell.py
unfazed/command/internal/startapp.py
unfazed/command/internal/startproject.py
unfazed/conf/__init__.py
unfazed/conf/base.py
unfazed/conf/decorators.py
unfazed/contrib/admin/__init__.py
unfazed/contrib/admin/admin.py
unfazed/contrib/admin/app.py
unfazed/contrib/admin/decorators.py
unfazed/contrib/admin/endpoints.py
unfazed/contrib/admin/models.py
unfazed/contrib/admin/routes.py
unfazed/contrib/admin/serializers.py
unfazed/contrib/admin/services.py
unfazed/contrib/admin/settings.py
unfazed/contrib/admin/registry/__init__.py
unfazed/contrib/admin/registry/collector.py
unfazed/contrib/admin/registry/decorators.py
unfazed/contrib/admin/registry/fields.py
unfazed/contrib/admin/registry/lifespan.py
unfazed/contrib/admin/registry/models.py
unfazed/contrib/admin/registry/schema.py
unfazed/contrib/admin/registry/utils.py
unfazed/contrib/admin/schema/__init__.py
unfazed/contrib/admin/schema/request.py
unfazed/contrib/admin/schema/response.py
unfazed/contrib/auth/admin.py
unfazed/contrib/auth/app.py
unfazed/contrib/auth/decorators.py
unfazed/contrib/auth/endpoints.py
unfazed/contrib/auth/middleware.py
unfazed/contrib/auth/mixin.py
unfazed/contrib/auth/models.py
unfazed/contrib/auth/routes.py
unfazed/contrib/auth/schema.py
unfazed/contrib/auth/serializers.py
unfazed/contrib/auth/services.py
unfazed/contrib/auth/settings.py
unfazed-0.0.18.dist-info/METADATA
unfazed-0.0.18.dist-info/WHEEL
unfazed-0.0.18.dist-info/entry_points.txt
unfazed-0.0.18.dist-info/licenses/LICENSE
unfazed-0.0.18.dist-info/RECORD
