Metadata-Version: 2.4
Name: unfazed
Version: 0.0.18
Summary: Production ready async python web framework
Author-email: "xin.zhou" <zhouxin576@gmail.com>
License: Copyright (c) 2024, unfazed-eco
License-File: LICENSE
Keywords: api-framework,asgi,async,django-inspired,fastapi-alternative,openapi,production-ready,swagger,tortoise-orm,web-framework
Classifier: Development Status :: 5 - Production/Stable
Classifier: Framework :: AsyncIO
Classifier: Intended Audience :: Developers
Classifier: License :: OSI Approved :: BSD License
Classifier: Operating System :: OS Independent
Classifier: Programming Language :: Python
Classifier: Programming Language :: Python :: 3
Classifier: Programming Language :: Python :: 3.12
Classifier: Programming Language :: Python :: 3.13
Classifier: Programming Language :: Python :: 3.14
Classifier: Topic :: Internet :: WWW/HTTP :: HTTP Servers
Classifier: Topic :: Internet :: WWW/HTTP :: WSGI :: Application
Classifier: Topic :: Software Development :: Libraries :: Application Frameworks
Classifier: Typing :: Typed
Requires-Python: >=3.12
Requires-Dist: aerich>=0.8.1
Requires-Dist: anyio>=4.7.0
Requires-Dist: asgiref>=3.8.1
Requires-Dist: click>=8.1.8
Requires-Dist: httpx>=0.28.1
Requires-Dist: itsdangerous>=2.2.0
Requires-Dist: jinja2>=3.1.5
Requires-Dist: openapi-pydantic>=0.5.1
Requires-Dist: orjson>=3.10.13
Requires-Dist: pydantic>=2.8.0
Requires-Dist: python-multipart>=0.0.20
Requires-Dist: redis>=5.2.1
Requires-Dist: starlette>=0.45.1
Requires-Dist: tortoise-orm>=0.23.0
Requires-Dist: uvicorn>=0.34.0
Provides-Extra: shell
Requires-Dist: ipython>=9.4.0; extra == 'shell'
